zoomlog/__init__.py
zoomlog-1.1.dist-info/LICENSE
zoomlog-1.1.dist-info/METADATA
zoomlog-1.1.dist-info/WHEEL
zoomlog-1.1.dist-info/top_level.txt
zoomlog-1.1.dist-info/RECORD
