Metadata-Version: 2.1
Name: zoomlog
Version: 1.1
Summary: Simple python logger
Home-page: UNKNOWN
Author: Zoom Developer
Author-email: sa-mp12345@yandex.ru
License: UNKNOWN
Platform: UNKNOWN
Classifier: Programming Language :: Python :: 3
Classifier: License :: OSI Approved :: MIT License
Classifier: Operating System :: OS Independent
Requires-Python: >=3.6
License-File: LICENSE
